HISTORY.md
LICENSE.txt
MANIFEST.in
README.rst
TODO.md
requirements-conda.txt
requirements.txt
setup.py
bcbio/__init__.py
bcbio/install.py
bcbio/setpath.py
bcbio/utils.py
bcbio/bam/__init__.py
bcbio/bam/callable.py
bcbio/bam/counts.py
bcbio/bam/coverage.py
bcbio/bam/cram.py
bcbio/bam/fasta.py
bcbio/bam/fastq.py
bcbio/bam/readstats.py
bcbio/bam/ref.py
bcbio/bam/skewer.py
bcbio/bam/trim.py
bcbio/bed/__init__.py
bcbio/broad/__init__.py
bcbio/broad/metrics.py
bcbio/broad/picardrun.py
bcbio/chipseq/__init__.py
bcbio/chipseq/macs2.py
bcbio/chipseq/peaks.py
bcbio/cwl/__init__.py
bcbio/cwl/create.py
bcbio/cwl/cwlutils.py
bcbio/cwl/defs.py
bcbio/cwl/hpc.py
bcbio/cwl/inspect.py
bcbio/cwl/main.py
bcbio/cwl/tool.py
bcbio/cwl/workflow.py
bcbio/data/umis/10x_v2-cb1.txt.gz
bcbio/data/umis/10x_v2-transform.json
bcbio/data/umis/dropseq-transform.json
bcbio/data/umis/harvard-indrop-v2-cb1.txt.gz
bcbio/data/umis/harvard-indrop-v2-cb2.txt.gz
bcbio/data/umis/harvard-indrop-v2-transform.json
bcbio/data/umis/harvard-indrop-v3-cb1.txt.gz
bcbio/data/umis/harvard-indrop-v3-cb2.txt.gz
bcbio/data/umis/harvard-indrop-v3-sample_barcodes.txt.gz
bcbio/data/umis/harvard-indrop-v3-transform.json
bcbio/data/umis/harvard-scrb-cb1.txt.gz
bcbio/data/umis/harvard-scrb-transform.json
bcbio/data/umis/icell8-cb1.txt.gz
bcbio/data/umis/icell8-transform.json
bcbio/data/umis/qiagen_smallRNA_umi-transform.json
bcbio/data/umis/surecell-cb1.txt.gz
bcbio/data/umis/surecell-cb2.txt.gz
bcbio/data/umis/surecell-cb3.txt.gz
bcbio/data/umis/surecell-transform.json
bcbio/distributed/__init__.py
bcbio/distributed/clargs.py
bcbio/distributed/clusterk.py
bcbio/distributed/ipython.py
bcbio/distributed/ipythontasks.py
bcbio/distributed/multi.py
bcbio/distributed/multitasks.py
bcbio/distributed/objectstore.py
bcbio/distributed/prun.py
bcbio/distributed/resources.py
bcbio/distributed/runfn.py
bcbio/distributed/split.py
bcbio/distributed/transaction.py
bcbio/galaxy/__init__.py
bcbio/galaxy/api.py
bcbio/galaxy/loc.py
bcbio_nextgen.egg-info/PKG-INFO
bcbio_nextgen.egg-info/SOURCES.txt
bcbio_nextgen.egg-info/dependency_links.txt
bcbio_nextgen.egg-info/not-zip-safe
bcbio_nextgen.egg-info/top_level.txt
