Metadata-Version: 1.0
Name: bcbio-nextgen
Version: 1.1.4
Summary: Best-practice pipelines for fully automated high throughput sequencing analysis
Home-page: https://github.com/bcbio/bcbio-nextgen
Author: bcbio community
Author-email: biovalidation@googlegroups.com
License: MIT
Platform: UNKNOWN
